MANIFEST.in
README.md
__init__.py
benchmark.py
example.py
likd_tree_py.cpp
pyproject.toml
setup.py
./__init__.py
./benchmark.py
./example.py
./likd_tree_py.cpp
./setup.py
./src/likd_tree.hpp
likd_tree.egg-info/PKG-INFO
likd_tree.egg-info/SOURCES.txt
likd_tree.egg-info/dependency_links.txt
likd_tree.egg-info/not-zip-safe
likd_tree.egg-info/requires.txt
likd_tree.egg-info/top_level.txt
src/likd_tree.hpp